CliRenderer/__init__.py
CliRenderer/__main__.py
CliRenderer/chartools.py
CliRenderer/colorer.py
CliRenderer/utils.py
CliRenderer-0.1.6.post4.dist-info/LICENSE
CliRenderer-0.1.6.post4.dist-info/METADATA
CliRenderer-0.1.6.post4.dist-info/WHEEL
CliRenderer-0.1.6.post4.dist-info/entry_points.txt
CliRenderer-0.1.6.post4.dist-info/top_level.txt
CliRenderer-0.1.6.post4.dist-info/RECORD
