Metadata-Version: 2.1
Name: CliRenderer
Version: 0.1.6.post4
Summary: A CLI tool to render unicode art in the terminal
Author-email: ultraflame4 <ultraflame4@gmail.com>
License: MIT License
Project-URL: Homepage, https://github.com/ultraflame4/CliR
Project-URL: Bug Tracker, https://github.com/ultraflame4/CliR/issues
Keywords: cli,unicode,art,render,terminal
Requires-Python: >=3.9
License-File: LICENSE
Requires-Dist: numpy ~=1.24.2
Requires-Dist: Pillow ~=9.5.0
Requires-Dist: rich ~=13.3.4
Requires-Dist: typer ~=0.9.0
Requires-Dist: imageio ~=2.27.0
Requires-Dist: validators ~=0.21.2
